{
  "timestamp": 1765979234.088767,
  "memory": {
    "healer-0": "validate_integrity_phase_4_6",
    "task-1": "build_phase_4_6_modules",
    "task-0": "optimize_learning_parameters",
    "task-2": "build_phase_4_6_modules",
    "healer-1": "validate_integrity_phase_4_6",
    "task-5": "optimize_learning_parameters",
    "healer-2": "validate_integrity_phase_4_6",
    "task-4": "optimize_learning_parameters",
    "healer-3": "validate_integrity_phase_4_6",
    "task-6": "build_phase_4_6_modules",
    "task-11": "optimize_learning_parameters",
    "healer-8": "validate_integrity_phase_4_6",
    "task-13": "optimize_learning_parameters",
    "task-8": "optimize_learning_parameters",
    "task-3": "optimize_learning_parameters",
    "healer-4": "validate_integrity_phase_4_6",
    "task-10": "build_phase_4_6_modules",
    "task-7": "optimize_learning_parameters",
    "healer-5": "validate_integrity_phase_4_6",
    "task-9": "optimize_learning_parameters",
    "healer-7": "validate_integrity_phase_4_6",
    "task-15": "build_phase_4_6_modules",
    "task-12": "optimize_learning_parameters",
    "healer-6": "validate_integrity_phase_4_6",
    "task-17": "build_phase_4_6_modules",
    "healer-11": "validate_integrity_phase_4_6",
    "task-16": "build_phase_4_6_modules",
    "healer-9": "validate_integrity_phase_4_6",
    "task-21": "optimize_learning_parameters",
    "task-19": "build_phase_4_6_modules",
    "task-14": "build_phase_4_6_modules",
    "healer-10": "validate_integrity_phase_4_6",
    "task-20": "build_phase_4_6_modules",
    "task-23": "optimize_learning_parameters",
    "healer-12": "validate_integrity_phase_4_6",
    "healer-14": "validate_integrity_phase_4_6",
    "healer-16": "validate_integrity_phase_4_6",
    "task-22": "optimize_learning_parameters",
    "healer-23": "validate_integrity_phase_4_6",
    "task-24": "build_phase_4_6_modules",
    "healer-21": "validate_integrity_phase_4_6",
    "task-18": "build_phase_4_6_modules",
    "healer-18": "validate_integrity_phase_4_6",
    "task-27": "build_phase_4_6_modules",
    "healer-26": "validate_integrity_phase_4_6",
    "task-26": "optimize_learning_parameters",
    "task-25": "optimize_learning_parameters",
    "task-29": "build_phase_4_6_modules",
    "task-28": "optimize_learning_parameters",
    "task-30": "optimize_learning_parameters",
    "task-34": "build_phase_4_6_modules",
    "healer-30": "validate_integrity_phase_4_6",
    "task-32": "build_phase_4_6_modules",
    "healer-28": "validate_integrity_phase_4_6",
    "task-33": "optimize_learning_parameters",
    "healer-19": "validate_integrity_phase_4_6",
    "task-31": "build_phase_4_6_modules",
    "task-36": "optimize_learning_parameters",
    "task-35": "build_phase_4_6_modules",
    "task-38": "optimize_learning_parameters",
    "healer-25": "validate_integrity_phase_4_6",
    "task-37": "optimize_learning_parameters",
    "task-41": "build_phase_4_6_modules",
    "healer-17": "validate_integrity_phase_4_6",
    "task-42": "optimize_learning_parameters",
    "task-39": "optimize_learning_parameters",
    "healer-24": "validate_integrity_phase_4_6",
    "task-40": "build_phase_4_6_modules",
    "healer-22": "validate_integrity_phase_4_6",
    "task-43": "build_phase_4_6_modules",
    "task-45": "optimize_learning_parameters"
  }
}