{
  "timestamp": 1765956844.7073412,
  "memory": {
    "healer-0": "validate_integrity_phase_4_6",
    "task-1": "build_phase_4_6_modules",
    "task-0": "build_phase_4_6_modules",
    "task-19": "optimize_learning_parameters",
    "task-7": "build_phase_4_6_modules",
    "healer-2": "validate_integrity_phase_4_6",
    "healer-3": "validate_integrity_phase_4_6",
    "healer-10": "validate_integrity_phase_4_6",
    "task-11": "optimize_learning_parameters",
    "task-22": "build_phase_4_6_modules",
    "task-3": "build_phase_4_6_modules",
    "healer-12": "validate_integrity_phase_4_6",
    "healer-5": "validate_integrity_phase_4_6",
    "healer-4": "validate_integrity_phase_4_6",
    "healer-1": "validate_integrity_phase_4_6",
    "task-8": "optimize_learning_parameters",
    "task-33": "optimize_learning_parameters",
    "healer-13": "validate_integrity_phase_4_6",
    "task-16": "optimize_learning_parameters",
    "healer-20": "validate_integrity_phase_4_6",
    "task-24": "optimize_learning_parameters",
    "task-25": "optimize_learning_parameters",
    "healer-22": "validate_integrity_phase_4_6",
    "healer-16": "validate_integrity_phase_4_6",
    "task-12": "optimize_learning_parameters",
    "healer-8": "validate_integrity_phase_4_6",
    "task-32": "optimize_learning_parameters",
    "healer-85": "validate_integrity_phase_4_6",
    "healer-29": "validate_integrity_phase_4_6",
    "task-9": "build_phase_4_6_modules",
    "task-31": "optimize_learning_parameters",
    "healer-92": "validate_integrity_phase_4_6",
    "task-2": "build_phase_4_6_modules",
    "task-10": "optimize_learning_parameters",
    "task-5": "optimize_learning_parameters",
    "task-21": "build_phase_4_6_modules",
    "task-17": "build_phase_4_6_modules",
    "healer-26": "validate_integrity_phase_4_6",
    "task-4": "optimize_learning_parameters",
    "task-20": "optimize_learning_parameters",
    "healer-30": "validate_integrity_phase_4_6",
    "healer-6": "validate_integrity_phase_4_6",
    "task-18": "build_phase_4_6_modules",
    "task-6": "build_phase_4_6_modules",
    "task-26": "build_phase_4_6_modules",
    "healer-58": "validate_integrity_phase_4_6",
    "task-14": "build_phase_4_6_modules",
    "healer-18": "validate_integrity_phase_4_6",
    "task-63": "build_phase_4_6_modules",
    "healer-39": "validate_integrity_phase_4_6",
    "healer-35": "validate_integrity_phase_4_6",
    "task-47": "optimize_learning_parameters",
    "healer-31": "validate_integrity_phase_4_6",
    "task-27": "optimize_learning_parameters",
    "healer-83": "validate_integrity_phase_4_6",
    "task-109": "optimize_learning_parameters",
    "task-62": "optimize_learning_parameters",
    "healer-54": "validate_integrity_phase_4_6",
    "task-52": "build_phase_4_6_modules",
    "task-15": "build_phase_4_6_modules",
    "healer-87": "validate_integrity_phase_4_6",
    "task-82": "build_phase_4_6_modules",
    "healer-66": "validate_integrity_phase_4_6",
    "task-146": "build_phase_4_6_modules",
    "healer-53": "validate_integrity_phase_4_6",
    "task-121": "build_phase_4_6_modules",
    "task-115": "optimize_learning_parameters",
    "healer-24": "validate_integrity_phase_4_6",
    "healer-21": "validate_integrity_phase_4_6",
    "task-28": "build_phase_4_6_modules",
    "healer-41": "validate_integrity_phase_4_6",
    "task-65": "optimize_learning_parameters",
    "task-72": "build_phase_4_6_modules",
    "healer-15": "validate_integrity_phase_4_6",
    "task-141": "optimize_learning_parameters",
    "healer-42": "validate_integrity_phase_4_6",
    "task-36": "optimize_learning_parameters",
    "task-154": "build_phase_4_6_modules",
    "task-227": "optimize_learning_parameters",
    "healer-40": "validate_integrity_phase_4_6",
    "healer-37": "validate_integrity_phase_4_6",
    "task-76": "build_phase_4_6_modules",
    "task-59": "optimize_learning_parameters",
    "task-60": "optimize_learning_parameters",
    "task-49": "optimize_learning_parameters",
    "task-77": "build_phase_4_6_modules",
    "task-85": "optimize_learning_parameters",
    "healer-60": "validate_integrity_phase_4_6",
    "task-87": "build_phase_4_6_modules",
    "task-73": "build_phase_4_6_modules",
    "healer-77": "validate_integrity_phase_4_6",
    "task-104": "optimize_learning_parameters",
    "task-69": "optimize_learning_parameters",
    "task-129": "build_phase_4_6_modules",
    "healer-71": "validate_integrity_phase_4_6",
    "task-161": "optimize_learning_parameters",
    "task-174": "optimize_learning_parameters",
    "task-97": "build_phase_4_6_modules",
    "task-236": "optimize_learning_parameters",
    "task-151": "build_phase_4_6_modules",
    "healer-28": "validate_integrity_phase_4_6",
    "task-54": "build_phase_4_6_modules",
    "healer-33": "validate_integrity_phase_4_6",
    "task-124": "optimize_learning_parameters",
    "task-132": "optimize_learning_parameters",
    "task-61": "build_phase_4_6_modules",
    "task-86": "build_phase_4_6_modules",
    "healer-57": "validate_integrity_phase_4_6",
    "healer-25": "validate_integrity_phase_4_6",
    "task-103": "build_phase_4_6_modules",
    "healer-47": "validate_integrity_phase_4_6",
    "task-200": "build_phase_4_6_modules",
    "task-90": "optimize_learning_parameters",
    "task-128": "optimize_learning_parameters",
    "task-244": "build_phase_4_6_modules",
    "healer-38": "validate_integrity_phase_4_6",
    "task-110": "build_phase_4_6_modules",
    "task-249": "optimize_learning_parameters",
    "task-198": "optimize_learning_parameters",
    "task-148": "build_phase_4_6_modules",
    "task-74": "build_phase_4_6_modules",
    "healer-79": "validate_integrity_phase_4_6",
    "healer-63": "validate_integrity_phase_4_6",
    "task-233": "build_phase_4_6_modules",
    "task-125": "optimize_learning_parameters",
    "healer-78": "validate_integrity_phase_4_6",
    "healer-93": "validate_integrity_phase_4_6",
    "task-50": "optimize_learning_parameters",
    "task-100": "build_phase_4_6_modules",
    "healer-67": "validate_integrity_phase_4_6",
    "task-296": "optimize_learning_parameters",
    "task-195": "build_phase_4_6_modules",
    "healer-14": "validate_integrity_phase_4_6",
    "task-267": "build_phase_4_6_modules",
    "healer-27": "validate_integrity_phase_4_6",
    "task-248": "optimize_learning_parameters",
    "task-46": "build_phase_4_6_modules",
    "healer-49": "validate_integrity_phase_4_6",
    "task-189": "optimize_learning_parameters",
    "task-251": "optimize_learning_parameters",
    "task-89": "optimize_learning_parameters",
    "healer-11": "validate_integrity_phase_4_6",
    "task-42": "optimize_learning_parameters",
    "task-80": "build_phase_4_6_modules",
    "healer-84": "validate_integrity_phase_4_6",
    "task-201": "optimize_learning_parameters",
    "task-118": "build_phase_4_6_modules",
    "healer-43": "validate_integrity_phase_4_6",
    "task-269": "build_phase_4_6_modules",
    "task-204": "build_phase_4_6_modules",
    "task-44": "optimize_learning_parameters",
    "task-223": "optimize_learning_parameters",
    "healer-17": "validate_integrity_phase_4_6",
    "healer-51": "validate_integrity_phase_4_6",
    "task-39": "optimize_learning_parameters",
    "task-187": "optimize_learning_parameters",
    "task-211": "build_phase_4_6_modules",
    "healer-9": "validate_integrity_phase_4_6",
    "healer-74": "validate_integrity_phase_4_6",
    "healer-95": "validate_integrity_phase_4_6",
    "task-218": "build_phase_4_6_modules",
    "task-215": "optimize_learning_parameters",
    "task-35": "build_phase_4_6_modules",
    "healer-7": "validate_integrity_phase_4_6",
    "task-127": "optimize_learning_parameters",
    "task-102": "optimize_learning_parameters",
    "healer-68": "validate_integrity_phase_4_6",
    "task-231": "build_phase_4_6_modules",
    "task-37": "build_phase_4_6_modules",
    "healer-88": "validate_integrity_phase_4_6",
    "task-175": "build_phase_4_6_modules",
    "healer-96": "validate_integrity_phase_4_6",
    "healer-81": "validate_integrity_phase_4_6",
    "task-209": "optimize_learning_parameters",
    "healer-69": "validate_integrity_phase_4_6",
    "task-202": "optimize_learning_parameters",
    "healer-82": "validate_integrity_phase_4_6",
    "task-245": "optimize_learning_parameters",
    "task-48": "build_phase_4_6_modules",
    "healer-73": "validate_integrity_phase_4_6",
    "task-270": "optimize_learning_parameters",
    "task-137": "build_phase_4_6_modules",
    "task-222": "optimize_learning_parameters",
    "healer-36": "validate_integrity_phase_4_6"
  }
}